Metadata-Version: 1.0
Name: TkDesinger
Version: 0.2
Summary: Tkinter Desinger to Python 3
Home-page: http://ppbe.ru
Author: FotonPC
Author-email: fototn-pc@inbox.ru
License: MIT
Platform: UNKNOWN
